src/__init__.py
src/certBuilder.py
src/certManager.py
src/conf.py
src/helpers.py
src/main.py
certsGenerator-0.4.5.post2.dist-info/LICENCE
certsGenerator-0.4.5.post2.dist-info/METADATA
certsGenerator-0.4.5.post2.dist-info/WHEEL
certsGenerator-0.4.5.post2.dist-info/entry_points.txt
certsGenerator-0.4.5.post2.dist-info/top_level.txt
certsGenerator-0.4.5.post2.dist-info/RECORD
