Metadata-Version: 2.1
Name: certsGenerator
Version: 0.4.5.post2
Summary: Certs generator made it simple
Home-page: https://github.com/t1m0t/certsGenerator
Author: Timothée BARON
Author-email: timothee.baron@protonmail.com
License: MIT
Project-URL: Code, https://github.com/t1m0t/certsGenerator
Project-URL: Issue tracker, https://github.com/t1m0t/certsGenerator/issues
Keywords: certs certificate x509 pyca cryptography crt
Platform: UNKNOWN
Classifier: Development Status :: 4 - Beta
Classifier: Intended Audience :: Developers
Classifier: License :: OSI Approved :: MIT License
Classifier: Intended Audience :: System Administrators
Classifier: Intended Audience :: Information Technology
Classifier: Natural Language :: English
Classifier: Operating System :: Unix
Classifier: Programming Language :: Python :: 3
Classifier: Topic :: Software Development :: Libraries
Requires-Python: >=3.7
Requires-Dist: click (==8.0.1)
Requires-Dist: cryptography (==3.4.8)
Requires-Dist: orjson (==3.6.3)
